polypy/__init__.py
polypy/_testutils.py
polypy/analysis.py
polypy/density.py
polypy/fig_params.py
polypy/msd.py
polypy/plotting.py
polypy/read.py
polypy/utils.py
polypy-0.8.dist-info/LICENSE
polypy-0.8.dist-info/METADATA
polypy-0.8.dist-info/WHEEL
polypy-0.8.dist-info/top_level.txt
polypy-0.8.dist-info/RECORD
