Metadata-Version: 2.1
Name: polypy
Version: 0.8
Summary: Molecular Dynamics analysis
Home-page: https://github.com/symmy596/Polypy
Author: Adam R. Symington
Author-email: ars44@bath.ac.uk
License: MIT license
Platform: UNKNOWN
Classifier: Programming Language :: Python
Classifier: Development Status :: 5 - Production/Stable
Classifier: Intended Audience :: Science/Research
Classifier: Operating System :: OS Independent
Classifier: Topic :: Scientific/Engineering
Requires-Dist: scipy
Requires-Dist: numpy
